CHANGES.txt
DanNote.txt
LICENSE.txt
MANIFEST.in
README.txt
TODO.txt
notes.txt
setup.py
bin/.RDFfromDX.py.swp
bin/RDFfromDX.py
bin/gridconvert.py
bin/.ipynb_checkpoints/gridconvert-checkpoint.ipynb
grid/__init__.py
grid/grid.py
grid.egg-info/PKG-INFO
grid.egg-info/SOURCES.txt
grid.egg-info/dependency_links.txt
grid.egg-info/requires.txt
grid.egg-info/top_level.txt
grid/data/shells.json
grid/data/points/10.pts
grid/data/points/100.pts
grid/data/points/12.pts
grid/data/points/13.pts
grid/data/points/15.pts
grid/data/points/150.pts
grid/data/points/17.pts
grid/data/points/19.pts
grid/data/points/200.pts
grid/data/points/23.pts
grid/data/points/50.pts
grid/data/points/70.pts
grid/data/points/notes.txt
grid/tests/__init__.py
grid/tests/grid_tests.py
grid/tests/data/TKRguv/h2o.guv
grid/tests/data/TKRguv/h2o.guv.sample
grid/tests/data/UxDATAfiles/UVDATA.sample
grid/tests/data/dxfiles/AlaDP_3DRISM_smallbuffer.dx.gz