Metadata-Version: 1.0
Name: grid
Version: 0.7.1
Summary: Volumetric data module
Home-page: UNKNOWN
Author: Daniel J. Sindhikara
Author-email: sindhikara@gmail.com
License: LGPL
Platform: UNKNOWN
